pyfus/__init__.py
pyfus/autoencoders.py
pyfus/ccf_v3_atlas_generation.py
pyfus/clustering.py
pyfus/correlation_analysis.py
pyfus/data_loading.py
pyfus/features_extraction.py
pyfus/global_variables.py
pyfus/quality_control.py
pyfus/quantification.py
pyfus/region_averaging_analysis.py
pyfus/registration.py
pyfus/utils.py
pyfus/atlases/__init__.py
pyfus/atlases/__pycache__/__init__.cpython-39.pyc
pyfus/atlases/atlases_lists/__init__.py
pyfus/atlases/atlases_lists/regions_ccf_v3_100_nolayersnoparts.txt
pyfus/atlases/atlases_lists/__pycache__/__init__.cpython-39.pyc
pyfus/atlases/atlases_npy/__init__.py
pyfus/atlases/atlases_npy/atlas_ccf_v3_100_contours.npy
pyfus/atlases/atlases_npy/atlas_ccf_v3_100_nolayersnoparts.npy
pyfus/atlases/atlases_npy/__pycache__/__init__.cpython-39.pyc
pyfus_lib-1.0.3.dist-info/METADATA
pyfus_lib-1.0.3.dist-info/WHEEL
pyfus_lib-1.0.3.dist-info/top_level.txt
pyfus_lib-1.0.3.dist-info/RECORD
